MANIFEST.in
setup.py
etc/colab/plugins.d/discourse.py
etc/colab/widgets.d/discourse_widgets.py
src/colab_discourse/__init__.py
src/colab_discourse/apps.py
src/colab_discourse/data_importer.py
src/colab_discourse/diazo.xml
src/colab_discourse/models.py
src/colab_discourse/search_indexes.py
src/colab_discourse/tasks.py
src/colab_discourse/urls.py
src/colab_discourse/views.py
src/colab_discourse.egg-info/PKG-INFO
src/colab_discourse.egg-info/SOURCES.txt
src/colab_discourse.egg-info/dependency_links.txt
src/colab_discourse.egg-info/not-zip-safe
src/colab_discourse.egg-info/requires.txt
src/colab_discourse.egg-info/top_level.txt
src/colab_discourse/management/__init__.py
src/colab_discourse/management/commands/__init__.py
src/colab_discourse/management/commands/fetch_data_discourse.py
src/colab_discourse/migrations/0001_initial.py
src/colab_discourse/migrations/0002_auto_20161202_1255.py
src/colab_discourse/migrations/__init__.py
src/colab_discourse/static/overrides-discourse.scss
src/colab_discourse/templates/proxy/discourse.html
src/colab_discourse/templates/search/post_search_preview.html
src/colab_discourse/templates/search/topic_search_preview.html
src/colab_discourse/templates/search/indexes/colab_discourse/discoursepost_text.txt
src/colab_discourse/templates/search/indexes/colab_discourse/discoursetopic_text.txt
src/colab_discourse/templates/widgets/discourse_home_section.html
src/colab_discourse/templates/widgets/discourse_navigation_link.html
src/colab_discourse/widgets/__init__.py
src/colab_discourse/widgets/home_section.py
src/colab_discourse/widgets/navigation_links.py